dockerflow/__init__.py
dockerflow/health.py
dockerflow/logging.py
dockerflow/version.py
dockerflow/checks/__init__.py
dockerflow/checks/messages.py
dockerflow/checks/registry.py
dockerflow/django/__init__.py
dockerflow/django/apps.py
dockerflow/django/checks.py
dockerflow/django/middleware.py
dockerflow/django/signals.py
dockerflow/django/views.py
dockerflow/fastapi/__init__.py
dockerflow/fastapi/middleware.py
dockerflow/fastapi/views.py
dockerflow/flask/__init__.py
dockerflow/flask/app.py
dockerflow/flask/signals.py
dockerflow/flask/checks/__init__.py
dockerflow/flask/checks/messages.py
dockerflow/sanic/__init__.py
dockerflow/sanic/app.py
dockerflow/sanic/checks.py
dockerflow-2026.1.26.dist-info/licenses/AUTHORS.rst
dockerflow-2026.1.26.dist-info/licenses/LICENSE
dockerflow-2026.1.26.dist-info/METADATA
dockerflow-2026.1.26.dist-info/WHEEL
dockerflow-2026.1.26.dist-info/top_level.txt
dockerflow-2026.1.26.dist-info/RECORD
